[
    {
        "PALETA": "ADIDAS MATCH Black 3.4 2025 (Pala)",
        "MARCA": "ADIDAS",
        "PRECIO_VENTA": "255950",
        "PRECIO_VENTA_TRANSFERENCIA": "209795",
        "IMG": "https://acdn-us.mitiendanube.com/stores/001/408/700/products/paleta-adidas-match-black-3-4-2025-0c9fdae48faf5a6ebe17398926268852-1024-1024.webp"
    },
    {
        "PALETA": "ADIDAS ADIPOWER A1 PADEL 2025 (Pala)",
        "MARCA": "ADIDAS",
        "PRECIO_VENTA": "459245",
        "PRECIO_VENTA_TRANSFERENCIA": "376431",
        "IMG": "https://padelmarket.com/cdn/shop/files/ADIDASADIPOWERA1PADEL2025_Pala_1_375x375_crop_center.jpg?v=1743156826"
    },
    {
        "PALETA": "ADIDAS ADIPOWER Carbon Ctrl 2025 (Pala)",
        "MARCA": "ADIDAS",
        "PRECIO_VENTA": "520884",
        "PRECIO_VENTA_TRANSFERENCIA": "426954",
        "IMG": "https://padelmarket.com/cdn/shop/files/Adipower_carbon_CTRL_AR1CA3FRONT_375x375_crop_center.png?v=1732883189"
    },
    {
        "PALETA": "ADIDAS ADIPOWER Control Multiweight PRO EDT 2024 ALEX RUIZ (Pala)",
        "MARCA": "ADIDAS",
        "PRECIO_VENTA": "513236",
        "PRECIO_VENTA_TRANSFERENCIA": "420685",
        "IMG": "https://padelmarket.com/cdn/shop/files/adidas_3e7ae559-155f-4f16-867c-1df9d7279ae4_375x375_crop_center.jpg?v=1728650907"
    },
    {
        "PALETA": "ADIDAS ADIPOWER CTRL 3.3 2024 (Pala)",
        "MARCA": "ADIDAS",
        "PRECIO_VENTA": "338769",
        "PRECIO_VENTA_TRANSFERENCIA": "277679",
        "IMG": "https://padelmarket.com/cdn/shop/files/8392_375x375_crop_center.jpg?v=1725950449"
    },
    {
        "PALETA": "ADIDAS ADIPOWER Multiweight Ctrl 3.4 2025 ALEX RUIZ (Pala)",
        "MARCA": "ADIDAS",
        "PRECIO_VENTA": "750319",
        "PRECIO_VENTA_TRANSFERENCIA": "615015",
        "IMG": "https://padelmarket.com/cdn/shop/files/Adipower_MTW_CTRL_AR1CA2FRONT_375x375_crop_center.png?v=1732883281"
    },
    {
        "PALETA": "ADIDAS CROSS IT 3.4 2025 (Pala)",
        "MARCA": "ADIDAS",
        "PRECIO_VENTA": "662369",
        "PRECIO_VENTA_TRANSFERENCIA": "542925",
        "IMG": "https://padelmarket.com/cdn/shop/files/Cross_it_3.4_AR1AA0FRONT_0d212813-e2f4-468f-b800-88617cddf11a_375x375_crop_center.png?v=1733214365"
    },
    {
        "PALETA": "ADIDAS CROSS IT Carbon Ctrl 3.4 2025 (Pala)",
        "MARCA": "ADIDAS",
        "PRECIO_VENTA": "540003",
        "PRECIO_VENTA_TRANSFERENCIA": "442626",
        "IMG": "https://padelmarket.com/cdn/shop/files/Cross_it_carbon_CTRL_AR1CATFRONT_375x375_crop_center.png?v=1732883632"
    },
    {
        "PALETA": "ADIDAS CROSS IT Ctrl 3.4 2025 (Pala)",
        "MARCA": "ADIDAS",
        "PRECIO_VENTA": "662369",
        "PRECIO_VENTA_TRANSFERENCIA": "542925",
        "IMG": "https://padelmarket.com/cdn/shop/files/Cross_it_CTRL_3.4_AR1CA5FRONT_375x375_crop_center.png?v=1732883741"
    },
    {
        "PALETA": "ADIDAS CROSS IT Team 2025 (Pala)",
        "MARCA": "ADIDAS",
        "PRECIO_VENTA": "405921",
        "PRECIO_VENTA_TRANSFERENCIA": "332722",
        "IMG": "https://padelmarket.com/cdn/shop/files/Cross_it_team_AR2AA1FRONT_375x375_crop_center.png?v=1733214851"
    },
    {
        "PALETA": "ADIDAS DRIVE Black 3.4 2025 (Pala)",
        "MARCA": "ADIDAS",
        "PRECIO_VENTA": "266443",
        "PRECIO_VENTA_TRANSFERENCIA": "218396",
        "IMG": "https://padelmarket.com/cdn/shop/files/Drive_black_3.4_AR5CA0FRONT_375x375_crop_center.png?v=1733222831"
    },
    {
        "PALETA": "ADIDAS DRIVE Grey 3.4 2025 (Pala)",
        "MARCA": "ADIDAS",
        "PRECIO_VENTA": "266443",
        "PRECIO_VENTA_TRANSFERENCIA": "218396",
        "IMG": "https://padelmarket.com/cdn/shop/files/Drive_Grey_3.4_AR5CA1FRONT_375x375_crop_center.png?v=1733222859"
    },
    {
        "PALETA": "ADIDAS DRIVE Light 3.4 2025 (Pala)",
        "MARCA": "ADIDAS",
        "PRECIO_VENTA": "266443",
        "PRECIO_VENTA_TRANSFERENCIA": "218396",
        "IMG": "https://padelmarket.com/cdn/shop/files/Drive_Light_3.4_AR5CA2FRONT_375x375_crop_center.png?v=1733222885"
    },
    {
        "PALETA": "ADIDAS KRM260 CARBON Naranja CTRL (Pala)",
        "MARCA": "ADIDAS",
        "PRECIO_VENTA": "330375",
        "PRECIO_VENTA_TRANSFERENCIA": "270799",
        "IMG": "https://padelmarket.com/cdn/shop/files/3056_375x375_crop_center.jpg?v=1725948739"
    },
    {
        "PALETA": "ADIDAS KRM260 CTRL 2022 (PALA)",
        "MARCA": "ADIDAS",
        "PRECIO_VENTA": "308413",
        "PRECIO_VENTA_TRANSFERENCIA": "252797",
        "IMG": "https://padelmarket.com/cdn/shop/files/8229_375x375_crop_center.jpg?v=1725948740"
    },
    {
        "PALETA": "ADIDAS MATCH Black 3.4 2025 (Pala)",
        "MARCA": "ADIDAS",
        "PRECIO_VENTA": "255950",
        "PRECIO_VENTA_TRANSFERENCIA": "209795",
        "IMG": "https://padelmarket.com/cdn/shop/files/Match_black_3.4_AR5GA0FRONT_375x375_crop_center.png?v=1733239265"
    },
    {
        "PALETA": "ADIDAS MATCH Blue 3.4 2025 (Pala)",
        "MARCA": "ADIDAS",
        "PRECIO_VENTA": "255950",
        "PRECIO_VENTA_TRANSFERENCIA": "209795",
        "IMG": "https://padelmarket.com/cdn/shop/files/Match_Blue_3.4_AR5GA2FRONT_375x375_crop_center.png?v=1733222936"
    },
    {
        "PALETA": "ADIDAS MATCH Light 3.4 2025 (Pala)",
        "MARCA": "ADIDAS",
        "PRECIO_VENTA": "255950",
        "PRECIO_VENTA_TRANSFERENCIA": "209795",
        "IMG": "https://padelmarket.com/cdn/shop/files/Match_Light_3.4_AR5GA1_FRONT_375x375_crop_center.png?v=1733223267"
    },
    {
        "PALETA": "ADIDAS METALBONE 09 2025 (Pala)",
        "MARCA": "ADIDAS",
        "PRECIO_VENTA": "459245",
        "PRECIO_VENTA_TRANSFERENCIA": "376431",
        "IMG": "https://padelmarket.com/cdn/shop/files/ADIDASMETALBONE092025_Pala_1_375x375_crop_center.jpg?v=1746001166"
    },
    {
        "PALETA": "ADIDAS METALBONE 3.3 2024 ALE GALAN (Pala)",
        "MARCA": "ADIDAS",
        "PRECIO_VENTA": "469261",
        "PRECIO_VENTA_TRANSFERENCIA": "384640",
        "IMG": "https://padelmarket.com/cdn/shop/files/8361_375x375_crop_center.jpg?v=1725950435"
    },
    {
        "PALETA": "ADIDAS METALBONE 3.4 2025 ALE GALAN (Pala)",
        "MARCA": "ADIDAS",
        "PRECIO_VENTA": "733111",
        "PRECIO_VENTA_TRANSFERENCIA": "600911",
        "IMG": "https://padelmarket.com/cdn/shop/files/Metalbone_3.4_AR1AA0FRONT_375x375_crop_center.png?v=1732883001"
    },
    {
        "PALETA": "ADIDAS METALBONE Carbon 3.3 2024 (Pala)",
        "MARCA": "ADIDAS",
        "PRECIO_VENTA": "424807",
        "PRECIO_VENTA_TRANSFERENCIA": "348203",
        "IMG": "https://padelmarket.com/cdn/shop/files/8384_375x375_crop_center.jpg?v=1725950438"
    },
    {
        "PALETA": "ADIDAS METALBONE Carbon 3.4 2025 (Pala)",
        "MARCA": "ADIDAS",
        "PRECIO_VENTA": "503676",
        "PRECIO_VENTA_TRANSFERENCIA": "412849",
        "IMG": "https://padelmarket.com/cdn/shop/files/Metalbone_carbon_3.4_AR1AA2_375x375_crop_center.png?v=1733246194"
    },
    {
        "PALETA": "ADIDAS METALBONE Carbon Ctrl 3.4 2025 (Pala)",
        "MARCA": "ADIDAS",
        "PRECIO_VENTA": "503676",
        "PRECIO_VENTA_TRANSFERENCIA": "412849",
        "IMG": "https://padelmarket.com/cdn/shop/files/Metalbone_carbon_CTRL_3.4_AR1CA1FRONT_375x375_crop_center.png?v=1732882959"
    },
    {
        "PALETA": "ADIDAS METALBONE HRD+ 2024 ALE GALAN (Pala)",
        "MARCA": "ADIDAS",
        "PRECIO_VENTA": "486468",
        "PRECIO_VENTA_TRANSFERENCIA": "398745",
        "IMG": "https://padelmarket.com/cdn/shop/files/8379_375x375_crop_center.jpg?v=1725950436"
    },
    {
        "PALETA": "ADIDAS METALBONE HRD+ 3.4 2025 ALE GALAN (Pala)",
        "MARCA": "ADIDAS",
        "PRECIO_VENTA": "733111",
        "PRECIO_VENTA_TRANSFERENCIA": "600911",
        "IMG": "https://padelmarket.com/cdn/shop/files/Metalbone_HRD_3.4_AR1AA1FRONT_375x375_crop_center.png?v=1732882815"
    },
    {
        "PALETA": "ADIDAS METALBONE Team 3.4 2025 (Pala)",
        "MARCA": "ADIDAS",
        "PRECIO_VENTA": "437398",
        "PRECIO_VENTA_TRANSFERENCIA": "358523",
        "IMG": "https://padelmarket.com/cdn/shop/files/Metalbone_team_3.4_AR2AA0FRONT_375x375_crop_center.png?v=1732883898"
    },
    {
        "PALETA": "ADIDAS METALBONE Team Light 3.4 2025 (Pala)",
        "MARCA": "ADIDAS",
        "PRECIO_VENTA": "437398",
        "PRECIO_VENTA_TRANSFERENCIA": "358523",
        "IMG": "https://padelmarket.com/cdn/shop/files/Metalbone_team_light_3.4_AR2CA0FRONT_375x375_crop_center.png?v=1733215126"
    },
    {
        "PALETA": "ADIDAS RX Series Lime 3.4 2025 (Pala)",
        "MARCA": "ADIDAS",
        "PRECIO_VENTA": "307292",
        "PRECIO_VENTA_TRANSFERENCIA": "251878",
        "IMG": "https://padelmarket.com/cdn/shop/files/RX_SERIES_LIME_3.4_AR3CAOFRONT_375x375_crop_center.png?v=1733222503"
    },
    {
        "PALETA": "ADIDAS RX Series Red 3.4 2025 (Pala)",
        "MARCA": "ADIDAS",
        "PRECIO_VENTA": "307292",
        "PRECIO_VENTA_TRANSFERENCIA": "251878",
        "IMG": "https://padelmarket.com/cdn/shop/files/RX_SERIES_RED_3.4_AR3CA2FRONT_375x375_crop_center.png?v=1733215346"
    },
    {
        "PALETA": "ADIDAS RX SERIES Rojo 2024 (Pala)",
        "MARCA": "ADIDAS",
        "PRECIO_VENTA": "245458",
        "PRECIO_VENTA_TRANSFERENCIA": "201195",
        "IMG": "https://padelmarket.com/cdn/shop/files/8404_375x375_crop_center.jpg?v=1725950461"
    },
    {
        "PALETA": "BULLPADEL HACK 02 Performance 2024 (Pala)",
        "MARCA": "BULLPADEL",
        "PRECIO_VENTA": "293723",
        "PRECIO_VENTA_TRANSFERENCIA": "240757",
        "IMG": "https://padelmarket.com/cdn/shop/files/7602_375x375_crop_center.jpg?v=1725950304"
    },
    {
        "PALETA": "BULLPADEL HACK 03 2024 PAQUITO NAVARRO (Pala)",
        "MARCA": "BULLPADEL",
        "PRECIO_VENTA": "445792",
        "PRECIO_VENTA_TRANSFERENCIA": "365403",
        "IMG": "https://padelmarket.com/cdn/shop/files/7591_375x375_crop_center.jpg?v=1725950265"
    },
    {
        "PALETA": "BULLPADEL HACK 03 Comfort 2023 (Pala)",
        "MARCA": "BULLPADEL",
        "PRECIO_VENTA": "331496",
        "PRECIO_VENTA_TRANSFERENCIA": "271718",
        "IMG": "https://padelmarket.com/cdn/shop/files/7959_375x375_crop_center.jpg?v=1725949647"
    },
    {
        "PALETA": "BULLPADEL HACK 03 Comfort 2024 (Pala)",
        "MARCA": "BULLPADEL",
        "PRECIO_VENTA": "342966",
        "PRECIO_VENTA_TRANSFERENCIA": "281120",
        "IMG": "https://padelmarket.com/cdn/shop/files/7588_375x375_crop_center.jpg?v=1725950265"
    },
    {
        "PALETA": "BULLPADEL HACK 04 PREMIER PADEL 2025 PAQUITO NAVARRO (Pala)",
        "MARCA": "BULLPADEL",
        "PRECIO_VENTA": "568683",
        "PRECIO_VENTA_TRANSFERENCIA": "466133",
        "IMG": "https://padelmarket.com/cdn/shop/files/BULLPADELHACK04PREMIERPADEL2025PAQUITONAVARRO_Pala_1_fb2ed2b1-4949-45f0-9ef3-bd2a055eadf3_375x375_crop_center.jpg?v=1738858228"
    },
    {
        "PALETA": "BULLPADEL HACK 04 Tour Final 2024 PAQUITO NAVARRO (Pala)",
        "MARCA": "BULLPADEL",
        "PRECIO_VENTA": "572507",
        "PRECIO_VENTA_TRANSFERENCIA": "469268",
        "IMG": "https://padelmarket.com/cdn/shop/files/hack04tf24_375x375_crop_center.jpg?v=1732885938"
    },
    {
        "PALETA": "BULLPADEL IONIC Control 2024 (Pala)",
        "MARCA": "BULLPADEL",
        "PRECIO_VENTA": "324079",
        "PRECIO_VENTA_TRANSFERENCIA": "265639",
        "IMG": "https://padelmarket.com/cdn/shop/files/7600_375x375_crop_center.jpg?v=1725950302"
    },
    {
        "PALETA": "BULLPADEL IONIC Power 2024 PABLO CARDONA (Pala)",
        "MARCA": "BULLPADEL",
        "PRECIO_VENTA": "335693",
        "PRECIO_VENTA_TRANSFERENCIA": "275158",
        "IMG": "https://padelmarket.com/cdn/shop/files/7598_375x375_crop_center.jpg?v=1725950275"
    },
    {
        "PALETA": "BULLPADEL IONIC Power 22 JAVI LEAL (Pala)",
        "MARCA": "BULLPADEL",
        "PRECIO_VENTA": "297920",
        "PRECIO_VENTA_TRANSFERENCIA": "244197",
        "IMG": "https://padelmarket.com/cdn/shop/files/8322_375x375_crop_center.jpg?v=1725949077"
    },
    {
        "PALETA": "BULLPADEL NEURON 2024 CHINGOTTO (Pala)",
        "MARCA": "BULLPADEL",
        "PRECIO_VENTA": "351360",
        "PRECIO_VENTA_TRANSFERENCIA": "288000",
        "IMG": "https://padelmarket.com/cdn/shop/files/8223_375x375_crop_center.jpg?v=1725950297"
    },
    {
        "PALETA": "BULLPADEL NEURON PREMIER PADEL 2025 FEDE CHINGOTTO (Pala)",
        "MARCA": "BULLPADEL",
        "PRECIO_VENTA": "541915",
        "PRECIO_VENTA_TRANSFERENCIA": "444193",
        "IMG": "https://padelmarket.com/cdn/shop/files/BULLPADELNEURONPREMIERPADEL2025FEDECHINGOTTO_Pala_1_888c91fb-ac4b-4ed4-bfaf-682dc7a004d0_375x375_crop_center.jpg?v=1738856005"
    },
    {
        "PALETA": "BULLPADEL NEURON Tour Final 2024 FEDE CHINGOTTO (Pala)",
        "MARCA": "BULLPADEL",
        "PRECIO_VENTA": "572507",
        "PRECIO_VENTA_TRANSFERENCIA": "469268",
        "IMG": "https://padelmarket.com/cdn/shop/files/neurontf24_375x375_crop_center.jpg?v=1732885990"
    },
    {
        "PALETA": "BULLPADEL VERTEX 02 X Rojo 2023 (Pala)",
        "MARCA": "BULLPADEL",
        "PRECIO_VENTA": "372345",
        "PRECIO_VENTA_TRANSFERENCIA": "305201",
        "IMG": "https://padelmarket.com/cdn/shop/files/7921_375x375_crop_center.jpg?v=1725949890"
    },
    {
        "PALETA": "BULLPADEL VERTEX 03 Comfort 2023 DI NENNO (Pala)",
        "MARCA": "BULLPADEL",
        "PRECIO_VENTA": "332473",
        "PRECIO_VENTA_TRANSFERENCIA": "272519",
        "IMG": "https://padelmarket.com/cdn/shop/files/8221_375x375_crop_center.jpg?v=1725949648"
    },
    {
        "PALETA": "BULLPADEL VERTEX 04 Comfort 2024 DI NENNO (Pala)",
        "MARCA": "BULLPADEL",
        "PRECIO_VENTA": "338769",
        "PRECIO_VENTA_TRANSFERENCIA": "277679",
        "IMG": "https://padelmarket.com/cdn/shop/files/BULLPADELVERTEX04Comfort2024DINENNO_Pala_1_375x375_crop_center.jpg?v=1739349350"
    },
    {
        "PALETA": "BULLPADEL VERTEX 04 Mexico 2024 (Pala)",
        "MARCA": "BULLPADEL",
        "PRECIO_VENTA": "574418",
        "PRECIO_VENTA_TRANSFERENCIA": "470835",
        "IMG": "https://padelmarket.com/cdn/shop/files/9595_375x375_crop_center.jpg?v=1725950857"
    },
    {
        "PALETA": "BULLPADEL VERTEX 04 Tour Final 2024 JUAN TELLO (Pala)",
        "MARCA": "BULLPADEL",
        "PRECIO_VENTA": "572507",
        "PRECIO_VENTA_TRANSFERENCIA": "469268",
        "IMG": "https://padelmarket.com/cdn/shop/files/vertex04tf24_375x375_crop_center.jpg?v=1732886093"
    },
    {
        "PALETA": "BULLPADEL XPLO PREMIER PADEL 2025 DI NENNO (Pala)",
        "MARCA": "BULLPADEL",
        "PRECIO_VENTA": "568683",
        "PRECIO_VENTA_TRANSFERENCIA": "466133",
        "IMG": "https://padelmarket.com/cdn/shop/files/BULLPADELXPLOPREMIERPADEL2025DINENNO_Pala_1_433feebe-ca9d-498f-af13-90fb9dd81ff0_375x375_crop_center.jpg?v=1738857509"
    },
    {
        "PALETA": "DROP SHOT AXION Attack 1.0 2025 JON SANZ (Pala)",
        "MARCA": "DROPSHOT",
        "PRECIO_VENTA": "601186",
        "PRECIO_VENTA_TRANSFERENCIA": "492775",
        "IMG": "https://padelmarket.com/cdn/shop/files/DROPSHOTAXIONAttack1.02025JONSANZ_Pala_1_375x375_crop_center.jpg?v=1741086093"
    },
    {
        "PALETA": "DROP SHOT AXION Comfort 2025 JON SANZ (Pala)",
        "MARCA": "DROPSHOT",
        "PRECIO_VENTA": "452087",
        "PRECIO_VENTA_TRANSFERENCIA": "370564",
        "IMG": "https://padelmarket.com/cdn/shop/files/DROPSHOTAXIONComfort2025JONSANZ_Pala_1_375x375_crop_center.jpg?v=1741090637"
    },
    {
        "PALETA": "DROP SHOT AXION Control 1.0 2025 JON SANZ (Pala)",
        "MARCA": "DROPSHOT",
        "PRECIO_VENTA": "466893",
        "PRECIO_VENTA_TRANSFERENCIA": "382699",
        "IMG": "https://padelmarket.com/cdn/shop/files/DROPSHOTAXIONControl1.02025JONSANZ_Pala_1_375x375_crop_center.jpg?v=1741088784"
    },
    {
        "PALETA": "DROP SHOT CANYON PRO Atttack 1.0 2025 PABLO LIMA (Pala)",
        "MARCA": "DROPSHOT",
        "PRECIO_VENTA": "585890",
        "PRECIO_VENTA_TRANSFERENCIA": "480238",
        "IMG": "https://padelmarket.com/cdn/shop/files/DROPSHOTCANYONPROAtttack1.02025PABLOLIMA_Pala_1_375x375_crop_center.jpg?v=1741084554"
    },
    {
        "PALETA": "DROP SHOT CANYON PRO Comfort 1.0 2025 PABLO LIMA (Pala)",
        "MARCA": "DROPSHOT",
        "PRECIO_VENTA": "433201",
        "PRECIO_VENTA_TRANSFERENCIA": "355083",
        "IMG": "https://padelmarket.com/cdn/shop/files/DROPSHOTCANYONPROComfort1.02025PABLOLIMA_Pala_1_375x375_crop_center.jpg?v=1741090954"
    },
    {
        "PALETA": "DROP SHOT CANYON PRO Control 1.0 2025 PABLO LIMA (Pala)",
        "MARCA": "DROPSHOT",
        "PRECIO_VENTA": "468875",
        "PRECIO_VENTA_TRANSFERENCIA": "384324",
        "IMG": "https://padelmarket.com/cdn/shop/files/DROPSHOTCANYONPROControl1.02025PABLOLIMA_Pala_1_375x375_crop_center.jpg?v=1741090073"
    },
    {
        "PALETA": "DROP SHOT CONQUEROR Attack 1.0 2025 (Pala)",
        "MARCA": "DROPSHOT",
        "PRECIO_VENTA": "601186",
        "PRECIO_VENTA_TRANSFERENCIA": "492775",
        "IMG": "https://padelmarket.com/cdn/shop/files/DROPSHOTCONQUERORAttack1.02025_Pala_1_375x375_crop_center.jpg?v=1741086771"
    },
    {
        "PALETA": "DROP SHOT CONQUEROR Comfort 1.0 2025 (Pala)",
        "MARCA": "DROPSHOT",
        "PRECIO_VENTA": "433201",
        "PRECIO_VENTA_TRANSFERENCIA": "355083",
        "IMG": "https://padelmarket.com/cdn/shop/files/DROPSHOTCONQUERORComfort1.02025_Pala_1_375x375_crop_center.jpg?v=1741091153"
    },
    {
        "PALETA": "DROP SHOT CONQUEROR Control 1.0 2025 (Pala)",
        "MARCA": "DROPSHOT",
        "PRECIO_VENTA": "468875",
        "PRECIO_VENTA_TRANSFERENCIA": "384324",
        "IMG": "https://padelmarket.com/cdn/shop/files/DROPSHOTCONQUERORControl1.02025_Pala_1_375x375_crop_center.jpg?v=1741090388"
    },
    {
        "PALETA": "DROP SHOT EXPLORER 8.0 2025 (Pala)",
        "MARCA": "DROPSHOT",
        "PRECIO_VENTA": "422709",
        "PRECIO_VENTA_TRANSFERENCIA": "346482",
        "IMG": "https://padelmarket.com/cdn/shop/files/DROPSHOTEXPLORER8.02025_Pala_1_375x375_crop_center.jpg?v=1741091717"
    },
    {
        "PALETA": "DROP SHOT EXPLORER PRO Attack 1.0 2025 LUCAS CAMPAGNOLO (Pala)",
        "MARCA": "DROPSHOT",
        "PRECIO_VENTA": "585890",
        "PRECIO_VENTA_TRANSFERENCIA": "480238",
        "IMG": "https://padelmarket.com/cdn/shop/files/DROPSHOTEXPLORERPROAttack1.02025LUCASCAMPAGNOLO_Pala_1_375x375_crop_center.jpg?v=1741086520"
    },
    {
        "PALETA": "DROP SHOT EXPLORER PRO Comfort 1.0 2025 (Pala)",
        "MARCA": "DROPSHOT",
        "PRECIO_VENTA": "433201",
        "PRECIO_VENTA_TRANSFERENCIA": "355083",
        "IMG": "https://padelmarket.com/cdn/shop/files/DROPSHOTEXPLORERPROComfort1.02025_Pala_1_375x375_crop_center.jpg?v=1741091338"
    },
    {
        "PALETA": "DROP SHOT EXPLORER PRO Control 1.0 2025 LUCAS CAMPAGNOLO (Pala)",
        "MARCA": "DROPSHOT",
        "PRECIO_VENTA": "468875",
        "PRECIO_VENTA_TRANSFERENCIA": "384324",
        "IMG": "https://padelmarket.com/cdn/shop/files/DROPSHOTEXPLORERPROControl1.02025LUCASCAMPAGNOLO_Pala_1_375x375_crop_center.jpg?v=1741089569"
    },
    {
        "PALETA": "DROP SHOT FURIA Attack 1.0 2025 (Pala)",
        "MARCA": "DROPSHOT",
        "PRECIO_VENTA": "490292",
        "PRECIO_VENTA_TRANSFERENCIA": "401879",
        "IMG": "https://padelmarket.com/cdn/shop/files/DROPSHOTFURIAAttack1.02025_Pala_1_375x375_crop_center.jpg?v=1741088444"
    },
    {
        "PALETA": "DROP SHOT FURIA Control 1.0 2025 (Pala)",
        "MARCA": "DROPSHOT",
        "PRECIO_VENTA": "490292",
        "PRECIO_VENTA_TRANSFERENCIA": "401879",
        "IMG": "https://padelmarket.com/cdn/shop/files/DROPSHOTFURIAControl1.02025_Pala_1_375x375_crop_center.jpg?v=1741089103"
    },
    {
        "PALETA": "DROP SHOT QUANTUM 2.0 2025 (Pala)",
        "MARCA": "DROPSHOT",
        "PRECIO_VENTA": "490292",
        "PRECIO_VENTA_TRANSFERENCIA": "401879",
        "IMG": "https://padelmarket.com/cdn/shop/files/DROPSHOTQUANTUM2.02025_Pala_1_375x375_crop_center.jpg?v=1741087636"
    },
    {
        "PALETA": "DROP SHOT RENEGADE LITE Control 2025 (Pala)",
        "MARCA": "DROPSHOT",
        "PRECIO_VENTA": "314708",
        "PRECIO_VENTA_TRANSFERENCIA": "257957",
        "IMG": "https://padelmarket.com/cdn/shop/files/DROPSHOTRENEGADELITEControl2025_Pala_1_375x375_crop_center.jpg?v=1741092396"
    },
    {
        "PALETA": "DROP SHOT X-DRIVE 2.0 2025 (Pala)",
        "MARCA": "DROPSHOT",
        "PRECIO_VENTA": "490292",
        "PRECIO_VENTA_TRANSFERENCIA": "401879",
        "IMG": "https://padelmarket.com/cdn/shop/files/DROPSHOTX-DRIVE2.02025_Pala_1_375x375_crop_center.jpg?v=1741088051"
    },
    {
        "PALETA": "NOX AT GENIUS Attack 18K 2024 AGUSTIN TAPIA (Pala)",
        "MARCA": "NOX",
        "PRECIO_VENTA": "403822",
        "PRECIO_VENTA_TRANSFERENCIA": "331002",
        "IMG": "https://padelmarket.com/cdn/shop/files/7608_375x375_crop_center.jpg?v=1725950218"
    },
    {
        "PALETA": "NOX AT10 GENIUS 12K 2025 by AGUSTIN TAPIA (Pala)",
        "MARCA": "NOX",
        "PRECIO_VENTA": "530443",
        "PRECIO_VENTA_TRANSFERENCIA": "434790",
        "IMG": "https://padelmarket.com/cdn/shop/files/PAT10GENIUS25_1_375x375_crop_center.png?v=1727953651"
    },
    {
        "PALETA": "NOX AT10 GENIUS 18K 2024 AGUSTIN TAPIA (Pala)",
        "MARCA": "NOX",
        "PRECIO_VENTA": "435300",
        "PRECIO_VENTA_TRANSFERENCIA": "356803",
        "IMG": "https://padelmarket.com/cdn/shop/files/7612_375x375_crop_center.jpg?v=1725950212"
    },
    {
        "PALETA": "NOX AT10 GENIUS 18K Alum 2025 by AGUSTIN TAPIA (Pala)",
        "MARCA": "NOX",
        "PRECIO_VENTA": "574418",
        "PRECIO_VENTA_TRANSFERENCIA": "470835",
        "IMG": "https://padelmarket.com/cdn/shop/files/PAT10GENIUS1825_1_375x375_crop_center.png?v=1728396459"
    },
    {
        "PALETA": "NOX AT10 GENIUS Attack 12K 2025 by AGUSTIN TAPIA (Pala)",
        "MARCA": "NOX",
        "PRECIO_VENTA": "503676",
        "PRECIO_VENTA_TRANSFERENCIA": "412849",
        "IMG": "https://padelmarket.com/cdn/shop/files/PAT10GENIUSAT25_1_458b7262-80db-4539-985c-18f77dcf6ffa_375x375_crop_center.png?v=1728399286"
    },
    {
        "PALETA": "NOX AT10 GENIUS Attack 18K Alum 2025 by AGUSTIN TAPIA (Pala)",
        "MARCA": "NOX",
        "PRECIO_VENTA": "459245",
        "PRECIO_VENTA_TRANSFERENCIA": "376431",
        "IMG": "https://padelmarket.com/cdn/shop/files/PAT10GENIUSAT1825_1_375x375_crop_center.png?v=1728399416"
    },
    {
        "PALETA": "NOX AT10 PRO CUP Comfort 2025 by AGUSTIN TAPIA (Pala)",
        "MARCA": "NOX",
        "PRECIO_VENTA": "359754",
        "PRECIO_VENTA_TRANSFERENCIA": "294880",
        "IMG": "https://padelmarket.com/cdn/shop/files/PAT10PCC25_1_375x375_crop_center.png?v=1728401837"
    },
    {
        "PALETA": "NOX AT10 PRO CUP Hard 2025 by AGUSTIN TAPIA (Pala)",
        "MARCA": "NOX",
        "PRECIO_VENTA": "359754",
        "PRECIO_VENTA_TRANSFERENCIA": "294880",
        "IMG": "https://padelmarket.com/cdn/shop/files/PAT10PCH25_1_375x375_crop_center.png?v=1728402247"
    },
    {
        "PALETA": "NOX EQUATION Advanced Series 2025 (Pala)",
        "MARCA": "NOX",
        "PRECIO_VENTA": "332473",
        "PRECIO_VENTA_TRANSFERENCIA": "272519",
        "IMG": "https://padelmarket.com/cdn/shop/files/PEQUADV25_1_375x375_crop_center.png?v=1728402561"
    },
    {
        "PALETA": "NOX FUTURE Attack 12K Alum NFA Series 2025 (Pala)",
        "MARCA": "NOX",
        "PRECIO_VENTA": "466893",
        "PRECIO_VENTA_TRANSFERENCIA": "382699",
        "IMG": "https://padelmarket.com/cdn/shop/files/NOXFUTUREAttack12KAlum2025_Pala_1_375x375_crop_center.jpg?v=1742473984"
    },
    {
        "PALETA": "NOX FUTURE Control 12K Alum NFA Series 2025 (Pala)",
        "MARCA": "NOX",
        "PRECIO_VENTA": "474997",
        "PRECIO_VENTA_TRANSFERENCIA": "389341",
        "IMG": "https://padelmarket.com/cdn/shop/files/NOXFUTUREControl12KAlum2025_Pala_1_375x375_crop_center.jpg?v=1742473472"
    },
    {
        "PALETA": "NOX FUTURE Hybrid 12K Alum NFA Series 2025 (Pala)",
        "MARCA": "NOX",
        "PRECIO_VENTA": "474997",
        "PRECIO_VENTA_TRANSFERENCIA": "389341",
        "IMG": "https://padelmarket.com/cdn/shop/files/NOXFUTUREHybrid12KAlum2025_Pala_1_375x375_crop_center.jpg?v=1742473795"
    },
    {
        "PALETA": "NOX ML10 PRO CUP Coorp. 2025 MIGUEL LAMPERTI (Pala)",
        "MARCA": "NOX",
        "PRECIO_VENTA": "319882",
        "PRECIO_VENTA_TRANSFERENCIA": "262199",
        "IMG": "https://padelmarket.com/cdn/shop/files/NOXML10PROCUPCoorp.2025MIGUELLAMPERTI_Pala_1_375x375_crop_center.jpg?v=1742470939"
    },
    {
        "PALETA": "NOX ML10 PRO CUP Rough Surface Edition 2025 MIGUEL LAMPERTI (Pala)",
        "MARCA": "NOX",
        "PRECIO_VENTA": "319882",
        "PRECIO_VENTA_TRANSFERENCIA": "262199",
        "IMG": "https://padelmarket.com/cdn/shop/files/NOXML10PROCUPRoughSurfaceEdition2025MIGUELLAMPERTI_Pala_1_375x375_crop_center.jpg?v=1742473210"
    },
    {
        "PALETA": "NOX ML10 QUANTUM 3K 2025 by MIGUEL LAMPERTI (Pala)",
        "MARCA": "NOX",
        "PRECIO_VENTA": "476453",
        "PRECIO_VENTA_TRANSFERENCIA": "390535",
        "IMG": "https://padelmarket.com/cdn/shop/files/PML10LUXQ25_1_375x375_crop_center.png?v=1728400659"
    },
    {
        "PALETA": "NOX NEXTGEN PRO Attack 3K NFA Series 2025 (Pala)",
        "MARCA": "NOX",
        "PRECIO_VENTA": "382837",
        "PRECIO_VENTA_TRANSFERENCIA": "313801",
        "IMG": "https://padelmarket.com/cdn/shop/files/NOXNEXTGENPROAttack3KNFASeries2025_Pala_1_375x375_crop_center.jpg?v=1742470455"
    },
    {
        "PALETA": "NOX NEXTGEN PRO Hybrid 3K NFA Series 2025 (Pala)",
        "MARCA": "NOX",
        "PRECIO_VENTA": "382837",
        "PRECIO_VENTA_TRANSFERENCIA": "313801",
        "IMG": "https://padelmarket.com/cdn/shop/files/NOXNEXTGENPROHybrid3KNFASeries2025_Pala_1_375x375_crop_center.jpg?v=1742470686"
    },
    {
        "PALETA": "NOX QUANTUM Carbon 12K 2025 (Pala)",
        "MARCA": "NOX",
        "PRECIO_VENTA": "503676",
        "PRECIO_VENTA_TRANSFERENCIA": "412849",
        "IMG": "https://padelmarket.com/cdn/shop/files/NOXQUANTUMCarbon12K2025_Pala_1_375x375_crop_center.jpg?v=1742475381"
    },
    {
        "PALETA": "NOX QUANTUM Cobalt 12K 2025 (Pala)",
        "MARCA": "NOX",
        "PRECIO_VENTA": "503676",
        "PRECIO_VENTA_TRANSFERENCIA": "412849",
        "IMG": "https://padelmarket.com/cdn/shop/files/NOXQUANTUMCobalt12K2025_Pala_1_375x375_crop_center.jpg?v=1742474963"
    },
    {
        "PALETA": "NOX X-ONE EVO RED 2023 (Pala)",
        "MARCA": "NOX",
        "PRECIO_VENTA": "304216",
        "PRECIO_VENTA_TRANSFERENCIA": "249357",
        "IMG": "https://padelmarket.com/cdn/shop/files/evo_375x375_crop_center.jpg?v=1732871002"
    },
    {
        "PALETA": "Pack NOX AT10 GENIUS Limited Edition AGUSTIN TAPIA 2025 (Pala)",
        "MARCA": "DESCONOCIDA",
        "PRECIO_VENTA": "706344",
        "PRECIO_VENTA_TRANSFERENCIA": "578970",
        "IMG": "https://padelmarket.com/cdn/shop/files/Capa6_4cf9540f-2764-4a28-a746-c2016cf38562_375x375_crop_center.jpg?v=1734690481"
    },
    {
        "PALETA": "STARVIE AQUILA Soft 2025 (Pala)",
        "MARCA": "STARVIE",
        "PRECIO_VENTA": "431103",
        "PRECIO_VENTA_TRANSFERENCIA": "353363",
        "IMG": "https://padelmarket.com/cdn/shop/files/Capa1_375x375_crop_center.jpg?v=1727767330"
    },
    {
        "PALETA": "STARVIE BRAVA PRO Mate 2025 (Pala)",
        "MARCA": "STARVIE",
        "PRECIO_VENTA": "466893",
        "PRECIO_VENTA_TRANSFERENCIA": "382699",
        "IMG": "https://padelmarket.com/cdn/shop/files/BRAVA01_72da057e-32e9-40bf-8459-f665cfb7ced9_375x375_crop_center.jpg?v=1738686532"
    },
    {
        "PALETA": "STARVIE BRAVA Soft Mate 2025 (Pala)",
        "MARCA": "STARVIE",
        "PRECIO_VENTA": "469261",
        "PRECIO_VENTA_TRANSFERENCIA": "384640",
        "IMG": "https://padelmarket.com/cdn/shop/files/BRAVA01_375x375_crop_center.jpg?v=1738686497"
    },
    {
        "PALETA": "STARVIE DRAX Soft 2025 (Pala)",
        "MARCA": "STARVIE",
        "PRECIO_VENTA": "538091",
        "PRECIO_VENTA_TRANSFERENCIA": "441058",
        "IMG": "https://padelmarket.com/cdn/shop/files/Capa8_37366433-923e-415c-9ec7-00913da3d515_375x375_crop_center.jpg?v=1729064160"
    },
    {
        "PALETA": "STARVIE KENTA Eternal Ultra Speed Soft 2024 (Pala)",
        "MARCA": "STARVIE",
        "PRECIO_VENTA": "466777",
        "PRECIO_VENTA_TRANSFERENCIA": "382604",
        "IMG": "https://padelmarket.com/cdn/shop/files/7644_375x375_crop_center.jpg?v=1725950338"
    },
    {
        "PALETA": "STARVIE RAPTOR Soft 2025 (Pala)",
        "MARCA": "STARVIE",
        "PRECIO_VENTA": "467349",
        "PRECIO_VENTA_TRANSFERENCIA": "383073",
        "IMG": "https://padelmarket.com/cdn/shop/files/Capa12_3c9a4234-a7f2-4f9d-9a64-4296c5c5f8a0_375x375_crop_center.jpg?v=1727878137"
    },
    {
        "PALETA": "STARVIE TRITON Ultra Speed Soft 2024 (Pala)",
        "MARCA": "STARVIE",
        "PRECIO_VENTA": "597362",
        "PRECIO_VENTA_TRANSFERENCIA": "489641",
        "IMG": "https://padelmarket.com/cdn/shop/files/8737_375x375_crop_center.jpg?v=1725950595"
    }
]